ramifice/__init__.py
ramifice/commons/__init__.py
ramifice/commons/general.py
ramifice/commons/indexes.py
ramifice/commons/many.py
ramifice/commons/one.py
ramifice/commons/tools.py
ramifice/commons/unit_manager.py
ramifice/fields/__init__.py
ramifice/fields/bool_field.py
ramifice/fields/choice_float_dyn_field.py
ramifice/fields/choice_float_field.py
ramifice/fields/choice_float_mult_dyn_field.py
ramifice/fields/choice_float_mult_field.py
ramifice/fields/choice_int_dyn_field.py
ramifice/fields/choice_int_field.py
ramifice/fields/choice_int_mult_dyn_field.py
ramifice/fields/choice_int_mult_field.py
ramifice/fields/choice_text_dyn_field.py
ramifice/fields/choice_text_field.py
ramifice/fields/choice_text_mult_dyn_field.py
ramifice/fields/choice_text_mult_field.py
ramifice/fields/color_field.py
ramifice/fields/date_field.py
ramifice/fields/date_time_field.py
ramifice/fields/email_field.py
ramifice/fields/file_field.py
ramifice/fields/float_field.py
ramifice/fields/general/__init__.py
ramifice/fields/general/choice_group.py
ramifice/fields/general/date_group.py
ramifice/fields/general/field.py
ramifice/fields/general/file_group.py
ramifice/fields/general/number_group.py
ramifice/fields/general/text_group.py
ramifice/fields/id_field.py
ramifice/fields/image_field.py
ramifice/fields/integer_field.py
ramifice/fields/ip_field.py
ramifice/fields/password_field.py
ramifice/fields/phone_field.py
ramifice/fields/slug_field.py
ramifice/fields/text_field.py
ramifice/fields/url_field.py
ramifice/models/__init__.py
ramifice/models/decorator.py
ramifice/models/model.py
ramifice/paladins/__init__.py
ramifice/paladins/add_valid.py
ramifice/paladins/check.py
ramifice/paladins/delete.py
ramifice/paladins/groups/__init__.py
ramifice/paladins/groups/bool_group.py
ramifice/paladins/groups/choice_group.py
ramifice/paladins/groups/date_group.py
ramifice/paladins/groups/file_group.py
ramifice/paladins/groups/id_group.py
ramifice/paladins/groups/img_group.py
ramifice-0.9.15.dist-info/licenses/LICENSE
ramifice-0.9.15.dist-info/WHEEL
ramifice-0.9.15.dist-info/METADATA
ramifice-0.9.15.dist-info/RECORD
