Metadata-Version: 2.4
Name: ramifice
Version: 0.9.15
Summary: ORM-pseudo-like API MongoDB for Python language.
Keywords: mongo,mongodb,pymongo,database,orm,ramifice
Author: kebasyaty
Author-email: kebasyaty <kebasyaty@gmail.com>
License-Expression: MIT
License-File: LICENSE
Classifier: Development Status :: 4 - Beta
Classifier: Intended Audience :: Developers
Classifier: License :: OSI Approved :: MIT License
Classifier: Programming Language :: Python :: 3
Classifier: Programming Language :: Python :: 3 :: Only
Classifier: Programming Language :: Python :: 3.12
Classifier: Programming Language :: Python :: 3.13
Classifier: Programming Language :: Python :: 3.14
Classifier: Programming Language :: Python :: Implementation :: CPython
Classifier: Topic :: Software Development :: Libraries
Classifier: Topic :: Software Development :: Libraries :: Python Modules
Classifier: Topic :: Database
Classifier: Typing :: Typed
Requires-Dist: anyio>=4.9.0
Requires-Dist: argon2-cffi>=25.1.0
Requires-Dist: babel>=2.17.0
Requires-Dist: email-validator>=2.2.0
Requires-Dist: orjson>=3.10.18
Requires-Dist: phonenumbers>=9.0.6
Requires-Dist: pillow>=11.2.1
Requires-Dist: pymongo>=4.13.0
Requires-Dist: python-dateutil>=2.9.0.post0
Requires-Dist: python-slugify>=8.0.4
Requires-Dist: pytz>=2025.2
Requires-Dist: pyyaml>=6.0.2
Requires-Dist: termcolor>=3.1.0
Requires-Dist: xloft>=0.1.6
Requires-Python: >=3.12, <4.0
Project-URL: Bug Tracker, https://github.com/kebasyaty/ramifice/issues
Project-URL: Changelog, https://github.com/kebasyaty/ramifice/blob/v0/CHANGELOG.md
Project-URL: Documentation, https://kebasyaty.github.io/ramifice/
Project-URL: Homepage, https://kebasyaty.github.io/ramifice/
Project-URL: Repository, https://github.com/kebasyaty/ramifice
Project-URL: Source, https://github.com/kebasyaty/ramifice
